AUTHORS
LICENSE
MANIFEST.in
README.rst
setup.cfg
setup.py
Redmine_CLI.egg-info/PKG-INFO
Redmine_CLI.egg-info/SOURCES.txt
Redmine_CLI.egg-info/dependency_links.txt
Redmine_CLI.egg-info/entry_points.txt
Redmine_CLI.egg-info/requires.txt
Redmine_CLI.egg-info/top_level.txt
redminecli/__init__.py
redminecli/main.py
tests/__init__.py