Metadata-Version: 1.1
Name: Redmine-CLI
Version: 0.0.5
Summary: A command-line utility to interact with Redmine
Home-page: http://github.com/yanjost/redmine-cli
Author: Yannick JOST
Author-email: yannick@yjost.com
License: MIT
Platform: UNKNOWN
Classifier: Development Status :: 3 - Alpha
Classifier: Environment :: Console
Classifier: Intended Audience :: Developers
Classifier: Intended Audience :: Information Technology
Classifier: License :: OSI Approved :: MIT License
Classifier: Operating System :: OS Independent
Classifier: Programming Language :: Python
